kalshi_clients.py
orderbook_manager.py
runner.py
ws_feed.py
kalshi_simple_ws_orderbook-1.0.0.dist-info/METADATA
kalshi_simple_ws_orderbook-1.0.0.dist-info/WHEEL
kalshi_simple_ws_orderbook-1.0.0.dist-info/top_level.txt
kalshi_simple_ws_orderbook-1.0.0.dist-info/RECORD
