Metadata-Version: 2.4
Name: kalshi-simple-ws-orderbook
Version: 1.0.0
Summary: High-performance Kalshi orderbook engine with async + threaded support
Author: Luke Palmieri
License: MIT
Requires-Python: >=3.9
